f5mkupy/__init__.py
f5mkupy/__main__.py
f5mkupy/cli.py
f5mkupy/f5mku.py
f5mkupy-1.0.1.dist-info/entry_points.txt
f5mkupy-1.0.1.dist-info/LICENSE
f5mkupy-1.0.1.dist-info/WHEEL
f5mkupy-1.0.1.dist-info/METADATA
f5mkupy-1.0.1.dist-info/RECORD
