Metadata-Version: 2.1
Name: f5mkupy
Version: 1.0.1
Summary: f5mkupy allows to encrypt and decrypt data using the format found in F5 BIG-IP bigip*.conf files with the key retrieved by f5mku -K.
Home-page: https://github.com/simonkowallik/f5mkupy
License: ISC
Keywords: F5,DevOps,Security
Author: Simon Kowallik
Author-email: sk-github@simonkowallik.com
Requires-Python: >=3.8,<4.0
Classifier: Development Status :: 5 - Production/Stable
Classifier: Intended Audience :: Developers
Classifier: Intended Audience :: Information Technology
Classifier: Intended Audience :: System Administrators
Classifier: License :: OSI Approved
Classifier: License :: OSI Approved :: ISC License (ISCL)
Classifier: Natural Language :: English
Classifier: Operating System :: OS Independent
Classifier: Programming Language :: Python
Classifier: Programming Language :: Python :: 3
Classifier: Programming Language :: Python :: 3.8
Classifier: Programming Language :: Python :: 3.9
Classifier: Programming Language :: Python :: 3.10
Classifier: Programming Language :: Python :: 3.11
Classifier: Programming Language :: Python :: 3
Classifier: Programming Language :: Python :: 3.6
Classifier: Topic :: Internet
Classifier: Topic :: Security
Classifier: Topic :: Software Development
Classifier: Topic :: Software Development :: Libraries
Classifier: Topic :: Software Development :: Libraries :: Python Modules
Classifier: Topic :: System
Classifier: Topic :: System :: Installation/Setup
Classifier: Topic :: System :: Networking
Classifier: Topic :: System :: Systems Administration
Requires-Dist: cryptography
Project-URL: Documentation, https://github.com/simonkowallik/f5mkupy
Project-URL: Repository, https://github.com/simonkowallik/f5mkupy
